torchblock/main.py
torchblock-0.1.1.dist-info/LICENSE
torchblock-0.1.1.dist-info/METADATA
torchblock-0.1.1.dist-info/WHEEL
torchblock-0.1.1.dist-info/RECORD
